[{"business_status": "OPERATIONAL", "geometry": {"location": {"lat": 51.10768829999999, "lng": 17.0510061}, "viewport": {"northeast": {"lat": 51.1090659302915, "lng": 17.0522216802915}, "southwest": {"lat": 51.1063679697085, "lng": 17.0495237197085}}}, "icon": "https://maps.gstatic.com/mapfiles/place_api/icons/v1/png_71/generic_business-71.png", "icon_background_color": "#7B9EB0", "icon_mask_base_uri": "https://maps.gstatic.com/mapfiles/place_api/icons/v2/generic_pinlet", "name": "Rekord Hale Namiotowe Sp. z o.o.", "photos": [{"height": 1365, "html_attributions": ["<a href=\"https://maps.google.com/maps/contrib/102100861597892147892\">Rekord Hale Namiotowe Sp. z o.o.</a>"], "photo_reference": "Aap_uEA9HN10yG_wgC254-EN52_AecoeyyF6LE55WcZNWy-huMBTW8-J-XoQCWGjk0Qg_sJywppCnT0E85NcnCddA2IFI_fqILB21VPK68do9osWPfapv7e2_2A-oWOUbT98W2GoI5Y8u6YLsyVvqv57hji_BYKHd7hgd3fqKE1esyXqI-Rr", "width": 2048}], "place_id": "ChIJG01bP3_CD0cRm9kl6K46de8", "plus_code": {"compound_code": "4352+3C Wroc\u0142aw, Poland", "global_code": "9F3V4352+3C"}, "rating": 3.7, "reference": "ChIJG01bP3_CD0cRm9kl6K46de8", "scope": "GOOGLE", "types": ["stadium", "gym", "health", "point_of_interest", "establishment"], "user_ratings_total": 22, "vicinity": "Mazowiecka 17, Wroc\u0142aw"}, {"business_status": "OPERATIONAL", "geometry": {"location": {"lat": 51.0983987, "lng": 17.0630834}, "viewport": {"northeast": {"lat": 51.09976973029151, "lng": 17.06495098029151}, "southwest": {"lat": 51.09707176970851, "lng": 17.0622530197085}}}, "icon": "https://maps.gstatic.com/mapfiles/place_api/icons/v1/png_71/stadium-71.png", "icon_background_color": "#4DB546", "icon_mask_base_uri": "https://maps.gstatic.com/mapfiles/place_api/icons/v2/stadium_pinlet", "name": "Stadion Sportowy \"O\u0142awka\"", "photos": [{"height": 3000, "html_attributions": ["<a href=\"https://maps.google.com/maps/contrib/114354600730037274962\">Andr\u00e9 Novaes</a>"], "photo_reference": "Aap_uEC7ZoaLEzAPea9d6cjcB2WfFjDlOWQpy56RtHdCHp3WL-5RTvjtj19z_NstaJQU48D2KmcsSztPlEKEnS-95e552BgWHN-9h-LDE-hQnNcC-k9lbCtkbwGSzwM0mQJNaOaOQAOLQmW1GhKxtoAs5tgJJ4r-fO8FIGpeqai3QJGyuzkU", "width": 4000}], "place_id": "ChIJeaKwpoXCD0cR4JsD1y6DLgA", "plus_code": {"compound_code": "33X7+96 Wroc\u0142aw, Poland", "global_code": "9F3V33X7+96"}, "rating": 4.3, "reference": "ChIJeaKwpoXCD0cR4JsD1y6DLgA", "scope": "GOOGLE", "types": ["stadium", "point_of_interest", "establishment"], "user_ratings_total": 318, "vicinity": "Na Niskich \u0141\u0105kach 8, Wroc\u0142aw"}]